regtester/RegExTest.py
regtester/RegExTestItem.py
regtester/RegExTester.py
regtester/TestItemResult.py
regtester/TestResponse.py
regtester/__init__.py
regtester/test_samples/ArtNumberTest.py
regtester/test_samples/LawTypeTest.py
regtester/test_samples/__init__.py
regtester-1.2.dist-info/METADATA
regtester-1.2.dist-info/WHEEL
regtester-1.2.dist-info/entry_points.txt
regtester-1.2.dist-info/top_level.txt
regtester-1.2.dist-info/RECORD
