Metadata-Version: 2.1
Name: regtester
Version: 1.2
Summary: RegEx Tester is a module to build unit test of regex in python
Home-page: https://github.com/bayethiernodiop/regtester
Author: Thierno Ibrahima DIOP
Author-email: thierno.diop@baamtu.com
License: MIT
Platform: UNKNOWN
Classifier: Development Status :: 4 - Beta
Classifier: License :: OSI Approved :: MIT License
Classifier: Programming Language :: Python
Classifier: Programming Language :: Python :: 3.7
Classifier: Topic :: Software Development :: Libraries
Classifier: Topic :: Software Development :: Libraries :: Python Modules
Classifier: Intended Audience :: Developers
Requires-Python: >=3.7
Requires-Dist: regex (==2019.11.1)
Requires-Dist: colorama (==0.4.1)
